flight_helper/__init__.py
flight_helper/models/__init__.py
flight_helper/models/dto/__init__.py
flight_helper/models/dto/booking.py
flight_helper/models/dto/http_schema.py
flight_helper/models/dto/itinerary.py
flight_helper/models/dto/passenger.py
flight_helper/models/dto/payment.py
flight_helper/models/dto/procurement.py
flight_helper/utils/__init__.py
flight_helper/utils/exception_utils.py
flight_helper/validator/__init__.py
flight_helper/validator/type_validator.py
flight_helper-0.4.9.dist-info/licenses/LICENSE
flight_helper-0.4.9.dist-info/METADATA
flight_helper-0.4.9.dist-info/WHEEL
flight_helper-0.4.9.dist-info/top_level.txt
flight_helper-0.4.9.dist-info/RECORD
