Metadata-Version: 2.4
Name: flight_helper
Version: 0.4.9
Summary: flight helper python package
Author-email: ckf10000 <ckf10000@sina.com>
License:                                  Apache License
Project-URL: Homepage, https://github.com/ckf10000/python-flight-helper
Project-URL: Source, https://github.com/ckf10000/python-flight-helper
Project-URL: Issues, https://github.com/ckf10000/python-flight-helper/issues
Requires-Python: >=3.12
License-File: LICENSE
Requires-Dist: aiohttp==3.13.2
Requires-Dist: pydantic==2.12.5
Dynamic: license-file
